pygoroutine/__init__.py
pygoroutine/app.py
pygoroutine-0.1.11.dist-info/licenses/LICENSE
pygoroutine-0.1.11.dist-info/METADATA
pygoroutine-0.1.11.dist-info/WHEEL
pygoroutine-0.1.11.dist-info/top_level.txt
pygoroutine-0.1.11.dist-info/RECORD
