Metadata-Version: 2.4
Name: pygoroutine
Version: 0.1.11
Summary: 🚀 Go-like concurrency in Python with channels and true parallelism.
Author-email: Anton Vice <anton96vice@gmail.com>
License: MIT License
Project-URL: Homepage, https://github.com/antonvice/pygoroutine
Project-URL: Bug Tracker, https://github.com/antonvice/pygoroutine/issues
Classifier: License :: OSI Approved :: MIT License
Classifier: Programming Language :: Python :: 3.10
Classifier: Programming Language :: Python :: 3.11
Classifier: Programming Language :: Python :: 3.12
Classifier: Topic :: Software Development :: Libraries :: Python Modules
Classifier: Intended Audience :: Developers
Requires-Python: >=3.7
License-File: LICENSE
Provides-Extra: test
Requires-Dist: pytest; extra == "test"
Requires-Dist: flake8; extra == "test"
Requires-Dist: black; extra == "test"
Requires-Dist: isort; extra == "test"
Requires-Dist: bump-my-version; extra == "test"
Dynamic: license-file
